gflex/__init__.py
gflex/__main__.py
gflex/_version.py
gflex/base.py
gflex/f1d.py
gflex/f2d.py
gflex/gflex.py
gflex-1.2.0.dist-info/AUTHORS.md
gflex-1.2.0.dist-info/LICENSE.md
gflex-1.2.0.dist-info/METADATA
gflex-1.2.0.dist-info/WHEEL
gflex-1.2.0.dist-info/entry_points.txt
gflex-1.2.0.dist-info/top_level.txt
gflex-1.2.0.dist-info/RECORD
