Metadata-Version: 2.1
Name: gflex
Version: 1.2.0
Summary: One- and two-dimensional plate bending, designed for Earth's lithosphere
Author-email: "Andrew D. Wickert" <awickert@umn.edu>, "Eric W. H. Hutton" <eric.hutton@colorado.edu>
Maintainer-email: "Andrew D. Wickert" <awickert@umn.edu>
License: GPL-3.0-only
Project-URL: homepage, https://github.com/awickert/gflex
Project-URL: documentation, https://github.com/awickert/gflex/blob/main/README.md
Project-URL: repository, https://github.com/awickert/gflex
Project-URL: changelog, https://github.com/awickert/gflex/blob/main/CHANGES.md
Keywords: geophysics,geology,geodynamics,lithosphere,isostasy,GRASS GIS
Classifier: Development Status :: 4 - Beta
Classifier: Intended Audience :: Science/Research
Classifier: License :: OSI Approved :: MIT License
Classifier: Operating System :: OS Independent
Classifier: Programming Language :: Cython
Classifier: Programming Language :: Python :: 3.10
Classifier: Programming Language :: Python :: 3.11
Classifier: Programming Language :: Python :: 3.12
Classifier: Programming Language :: Python :: 3
Classifier: Programming Language :: Python :: Implementation :: CPython
Classifier: Topic :: Scientific/Engineering :: Physics
Requires-Python: >=3.10
License-File: LICENSE.md
License-File: AUTHORS.md
Requires-Dist: matplotlib
Requires-Dist: numpy
Requires-Dist: scipy
Provides-Extra: dev
Requires-Dist: nox ; extra == 'dev'
Provides-Extra: testing
Requires-Dist: pytest ; extra == 'testing'
